docs/examples/ior/local/ior_bayesian.yaml
docs/examples/ior/local/ior_exhaustive_vars.yaml
docs/examples/ior/local/ior_random.yaml
docs/examples/ior/local/ior_simple.yaml
docs/examples/ior/local/ior_with_reporting.yaml
docs/examples/ior/scripts/__init__.py
docs/examples/ior/scripts/install_ior.sh
docs/examples/ior/scripts/ior_parser.py
docs/examples/ior/scripts/ior_slurm.sh
docs/examples/ior/slurm/ior_bayesian_slurm.yaml
docs/examples/ior/slurm/ior_simple_slurm.yaml
docs/examples/mdtest/local/mdtest_local.yaml
docs/examples/mdtest/scripts/mdtest_parser.py
docs/examples/mdtest/slurm/mdtest_slurm.yaml
iops/VERSION
iops/__init__.py
iops/__main__.py
iops/logger.py
iops/main.py
iops/archive/__init__.py
iops/archive/core.py
iops/archive/filter.py
iops/archive/manifest.py
iops/cache/__init__.py
iops/cache/execution_cache.py
iops/cache/rebuild.py
iops/config/__init__.py
iops/config/loader.py
iops/config/models.py
iops/execution/__init__.py
iops/execution/constraints.py
iops/execution/executors.py
iops/execution/matrix.py
iops/execution/parser.py
iops/execution/planner.py
iops/execution/runner.py
iops/reporting/__init__.py
iops/reporting/config_template.py
iops/reporting/plots.py
iops/reporting/report_generator.py
iops/results/__init__.py
iops/results/find.py
iops/results/watch.py
iops/results/writer.py
iops/setup/__init__.py
iops/setup/template_full.yaml
iops/setup/templates.py
iops/setup/wizard.py
iops/setup/templates/ior_local.yaml
iops/setup/templates/ior_slurm.yaml
iops/setup/templates/mdtest_local.yaml
iops/setup/templates/mdtest_slurm.yaml
iops_benchmark-3.5.0.dist-info/licenses/LICENSE
iops_benchmark-3.5.0.dist-info/METADATA
iops_benchmark-3.5.0.dist-info/WHEEL
iops_benchmark-3.5.0.dist-info/entry_points.txt
iops_benchmark-3.5.0.dist-info/top_level.txt
iops_benchmark-3.5.0.dist-info/RECORD
