Metadata-Version: 2.4
Name: iops-benchmark
Version: 3.5.0
Summary: A generic benchmark orchestration framework for automated parametric experiments
Home-page: https://gitlab.inria.fr/lgouveia/iops
Author: TADAAM - INRIA Bordeaux
Author-email: TADAAM - INRIA Bordeaux <luan.teylo@inria.fr>
License: BSD-3-Clause
Project-URL: Homepage, https://gitlab.inria.fr/lgouveia/iops
Project-URL: Documentation, https://gitlab.inria.fr/lgouveia/iops
Project-URL: Repository, https://gitlab.inria.fr/lgouveia/iops
Project-URL: Issues, https://gitlab.inria.fr/lgouveia/iops/-/issues
Keywords: benchmark,performance,testing,parametric,sweep,hpc,slurm
Classifier: Development Status :: 4 - Beta
Classifier: Intended Audience :: Science/Research
Classifier: Intended Audience :: Developers
Classifier: Topic :: Software Development :: Testing
Classifier: Topic :: System :: Benchmark
Classifier: Programming Language :: Python :: 3
Classifier: Programming Language :: Python :: 3.10
Classifier: Programming Language :: Python :: 3.11
Classifier: Programming Language :: Python :: 3.12
Classifier: Operating System :: POSIX :: Linux
Classifier: Operating System :: MacOS
Requires-Python: >=3.10
License-File: LICENSE
Requires-Dist: pyyaml
Requires-Dist: scikit-optimize
Requires-Dist: pandas>=2.1.0
Requires-Dist: jinja2>=3.0.0
Requires-Dist: plotly
Provides-Extra: parquet
Requires-Dist: pyarrow; extra == "parquet"
Provides-Extra: watch
Requires-Dist: rich; extra == "watch"
Provides-Extra: plots
Requires-Dist: kaleido; extra == "plots"
Dynamic: author
Dynamic: home-page
Dynamic: license-file
Dynamic: requires-python
